CHANGELOG.md
LICENSE
README.md
uscodekit/__init__.py
uscodekit/configs.py
uscodekit/data/.gitkeep
uscodekit/data/geo/.gitkeep
uscodekit/data/naics/2022/naics.bin
uscodekit/phone.py
uscodekit/services/geo.py
uscodekit/services/naics.py
uscodekit/setup.py
uscodekit/shared/__init__.py
uscodekit/shared/file.py
uscodekit/shared/jsonfile.py
uscodekit/zip_code.py
uscodekit-2024.2.2.dist-info/LICENSE
uscodekit-2024.2.2.dist-info/METADATA
uscodekit-2024.2.2.dist-info/WHEEL
uscodekit-2024.2.2.dist-info/entry_points.txt
uscodekit-2024.2.2.dist-info/RECORD
