Metadata-Version: 2.1
Name: uscodekit
Version: 2024.2.2
Summary: A Python package for US codes validation, extraction, formatting, cleaning, and more.
Home-page: https://github.com/rk4bir/USCodeKit
License: MIT
Author: Raihan Kabir
Author-email: r.kabir01@proton.me
Requires-Python: >=3.9
Classifier: License :: OSI Approved :: MIT License
Classifier: Programming Language :: Python :: 3
Classifier: Programming Language :: Python :: 3.9
Classifier: Programming Language :: Python :: 3.10
Classifier: Programming Language :: Python :: 3.11
Classifier: Programming Language :: Python :: 3.12
Requires-Dist: cryptography (>=43.0.3,<44.0.0)
Project-URL: Repository, https://github.com/rk4bir/USCodeKit
